ocr/__init__.py
ocr/aadhaar_card.py
ocr/fetch_data.py
ocr/image_preprocessor.py
ocr/pan_card.py
ocr_pro-0.1.3.dist-info/METADATA
ocr_pro-0.1.3.dist-info/WHEEL
ocr_pro-0.1.3.dist-info/top_level.txt
ocr_pro-0.1.3.dist-info/RECORD
