Metadata-Version: 2.4
Name: ocr-pro
Version: 0.1.3
Summary: OCR extractor for PAN and Aadhaar card details
Home-page: https://github.com/KoustubhPK/ocr-pro
Author: KoustubhPK
Author-email: koustubhpk@gmail.com
Classifier: Programming Language :: Python :: 3
Classifier: License :: OSI Approved :: MIT License
Classifier: Operating System :: Microsoft :: Windows
Requires-Python: >=3.8
Requires-Dist: pytesseract
Requires-Dist: pillow
Dynamic: author
Dynamic: author-email
Dynamic: classifier
Dynamic: description
Dynamic: description-content-type
Dynamic: home-page
Dynamic: requires-dist
Dynamic: requires-python
Dynamic: summary
